{"nodes": [{"id": "js_storage_storage", "label": "Storage Module (IndexedDB)", "file_type": "code", "source_file": "js/storage.js", "source_location": "1-179", "source_url": null, "captured_at": null, "author": null, "contributor": null}, {"id": "js_storage_open", "label": "Storage.open (IndexedDB init)", "file_type": "code", "source_file": "js/storage.js", "source_location": "12-37", "source_url": null, "captured_at": null, "author": null, "contributor": null}, {"id": "js_storage_templates", "label": "Storage Templates Store", "file_type": "code", "source_file": "js/storage.js", "source_location": "51-90", "source_url": null, "captured_at": null, "author": null, "contributor": null}, {"id": "js_storage_sessions", "label": "Storage Sessions Store", "file_type": "code", "source_file": "js/storage.js", "source_location": "92-113", "source_url": null, "captured_at": null, "author": null, "contributor": null}, {"id": "js_storage_drafts", "label": "Storage Drafts Store (autosave)", "file_type": "code", "source_file": "js/storage.js", "source_location": "116-128", "source_url": null, "captured_at": null, "author": null, "contributor": null}, {"id": "js_storage_suggestions", "label": "Storage Suggestions Store (frequent values)", "file_type": "code", "source_file": "js/storage.js", "source_location": "131-159", "source_url": null, "captured_at": null, "author": null, "contributor": null}, {"id": "js_storage_lockedfields", "label": "Storage LockedFields Store", "file_type": "code", "source_file": "js/storage.js", "source_location": "162-170", "source_url": null, "captured_at": null, "author": null, "contributor": null}, {"id": "indexeddb", "label": "IndexedDB (browser storage)", "file_type": "concept", "source_file": "js/storage.js", "source_location": "15", "source_url": null, "captured_at": null, "author": null, "contributor": null}], "edges": [{"source": "js_storage_storage", "target": "indexeddb", "relation": "calls", "confidence": "EXTRACTED", "confidence_score": 1.0, "source_file": "js/storage.js", "source_location": "15", "weight": 1.0}, {"source": "js_storage_open", "target": "indexeddb", "relation": "calls", "confidence": "EXTRACTED", "confidence_score": 1.0, "source_file": "js/storage.js", "source_location": "15", "weight": 1.0}, {"source": "js_storage_drafts", "target": "js_app_draft_resume_concept", "relation": "rationale_for", "confidence": "INFERRED", "confidence_score": 0.85, "source_file": "js/storage.js", "source_location": "116-128", "weight": 0.9}, {"source": "js_storage_lockedfields", "target": "js_app_lockedfields_concept", "relation": "rationale_for", "confidence": "INFERRED", "confidence_score": 0.85, "source_file": "js/storage.js", "source_location": "162-170", "weight": 0.9}, {"source": "js_storage_suggestions", "target": "js_app_setactivefield", "relation": "shares_data_with", "confidence": "INFERRED", "confidence_score": 0.85, "source_file": "js/storage.js", "source_location": "131-159", "weight": 0.8}], "hyperedges": [{"id": "offline_persistence_layer", "label": "Offline Persistence Layer (IndexedDB stores)", "nodes": ["js_storage_storage", "js_storage_templates", "js_storage_sessions", "js_storage_drafts", "js_storage_suggestions", "js_storage_lockedfields"], "relation": "form", "confidence": "EXTRACTED", "confidence_score": 1.0, "source_file": "js/storage.js"}]}